asyncops/__init__.py
asyncops-0.1.0.dist-info/WHEEL
asyncops-0.1.0.dist-info/METADATA
asyncops-0.1.0.dist-info/RECORD
