Metadata-Version: 2.1
Name: asyncops
Version: 0.1.0
Summary: The library for async operations.
Author: Zeb Taylor
Author-email: zceboys@gmail.com
Requires-Python: >=3.10,<4.0
Classifier: Programming Language :: Python :: 3
Classifier: Programming Language :: Python :: 3.10
Requires-Dist: contextvars (>=2.4,<3.0)
